EAS2Text/CCL-us.json
EAS2Text/EAS2Text.py
EAS2Text/__init__.py
EAS2Text/same-ca.json
EAS2Text/same-us.json
EAS2Text/wfo-us.json
EAS2Text_Remastered-0.1.25.1.dist-info/LICENSE
EAS2Text_Remastered-0.1.25.1.dist-info/METADATA
EAS2Text_Remastered-0.1.25.1.dist-info/WHEEL
EAS2Text_Remastered-0.1.25.1.dist-info/top_level.txt
EAS2Text_Remastered-0.1.25.1.dist-info/RECORD
