Metadata-Version: 2.1
Name: EAS2Text-Remastered
Version: 0.1.25.1
Summary: A Python library to convert raw EAS header data to a human readable text - Remastered
Home-page: https://github.com/Newton-Communications/E2T
Author: secludedhusky
Author-email: secludedhusky@chesbaycommunications.com
License: ODbL-1.0
Keywords: eas alerting emergency-alert-system
Classifier: Development Status :: 5 - Production/Stable
Classifier: License :: Other/Proprietary License
Classifier: Programming Language :: Python
Classifier: Programming Language :: Python :: 3.7
Classifier: Programming Language :: Python :: 3.8
Classifier: Programming Language :: Python :: 3.9
Classifier: Programming Language :: Python :: 3.10
Classifier: Programming Language :: Python :: 3.11
Classifier: Intended Audience :: Developers
Classifier: Operating System :: OS Independent
Classifier: Topic :: Software Development :: Libraries
Classifier: Topic :: Utilities
License-File: LICENSE
